discord_command/__init__.py
discord_command/application_command.py
discord_flask/Interactions.py
discord_flask/__init__.py
discord_flask/utils.py
discord_interaction/__init__.py
discord_interaction/interaction.py
discord_interaction/interaction_response.py
discord_interaction/member.py
discord_interaction/utils.py
discord_interactions/__init__.py
discord_interactions/application_command.py
discord_interactions/client.py
discord_interactions/interaction.py
discord_interactions/interaction_response.py
discord_interactions/member.py
discord_interactions/message_component.py
discord_interactions/models.py
discord_interactions/permissions.py
discord_interactions/utils.py
discord_interactions/flask_ext/Interactions.py
discord_interactions/flask_ext/__init__.py
discord_interactions/flask_ext/context.py
discord_interactions/flask_ext/interactions.py
discord_interactions/flask_ext/utils.py
discord_interactions/ocm/__init__.py
discord_interactions/ocm/command.py
discord_interactions.py-0.0.8.dist-info/LICENSE
discord_interactions.py-0.0.8.dist-info/METADATA
discord_interactions.py-0.0.8.dist-info/WHEEL
discord_interactions.py-0.0.8.dist-info/top_level.txt
discord_interactions.py-0.0.8.dist-info/RECORD
