Metadata-Version: 2.1
Name: discord-interactions.py
Version: 0.0.8
Summary: A library around the Discord Interactions API
Home-page: https://github.com/LiBa001/discord-interactions.py
Author: Linus Bartsch
Author-email: pypi@libasoft.de
License: MIT
Keywords: discord discord-py discord-bot wrapper
Platform: UNKNOWN
Classifier: Development Status :: 1 - Planning
Classifier: Environment :: Web Environment
Classifier: Framework :: Flask
Classifier: Intended Audience :: Developers
Classifier: License :: OSI Approved :: MIT License
Classifier: Programming Language :: Python :: 3.8
Classifier: Programming Language :: Python :: 3.9
Classifier: Programming Language :: Python :: Implementation :: CPython
Classifier: Topic :: Internet
Classifier: Topic :: Software Development :: Libraries
Requires-Python: >=3.8
Requires-Dist: flask
Requires-Dist: pynacl
Requires-Dist: requests
